Metadata-Version: 2.1
Name: gobang
Version: 0.1.0
Summary: A Gobang(also known as "Five in a Row" and "Gomoku") game equipped with AlphaGo-liked AI.
Home-page: https://github.com/jidasheng/gobang
Author: Dasheng Ji
Author-email: jidasheng@qq.com
License: MIT
Platform: UNKNOWN
Classifier: Programming Language :: Python :: 3
Classifier: License :: OSI Approved :: MIT License
Classifier: Operating System :: OS Independent
